flytekitplugins_huggingface-1.16.12-py3.14-nspkg.pth
flytekitplugins/huggingface/__init__.py
flytekitplugins/huggingface/sd_transformers.py
flytekitplugins_huggingface-1.16.12.dist-info/METADATA
flytekitplugins_huggingface-1.16.12.dist-info/WHEEL
flytekitplugins_huggingface-1.16.12.dist-info/entry_points.txt
flytekitplugins_huggingface-1.16.12.dist-info/namespace_packages.txt
flytekitplugins_huggingface-1.16.12.dist-info/top_level.txt
flytekitplugins_huggingface-1.16.12.dist-info/RECORD
